laurelin_ldap-2.0.4-py3.7-nspkg.pth
laurelin/extensions/base_schema.py
laurelin/extensions/descattrs.py
laurelin/extensions/netgroups.py
laurelin/extensions/pagedresults.py
laurelin/ldap/__init__.py
laurelin/ldap/attributetype.py
laurelin/ldap/attrsdict.py
laurelin/ldap/attrvaluelist.py
laurelin/ldap/base.py
laurelin/ldap/config.py
laurelin/ldap/constants.py
laurelin/ldap/controls.py
laurelin/ldap/exceptions.py
laurelin/ldap/filter.py
laurelin/ldap/ldapobject.py
laurelin/ldap/modify.py
laurelin/ldap/net.py
laurelin/ldap/objectclass.py
laurelin/ldap/protoutils.py
laurelin/ldap/rfc4511.py
laurelin/ldap/rfc4512.py
laurelin/ldap/rfc4514.py
laurelin/ldap/rfc4518.py
laurelin/ldap/rules.py
laurelin/ldap/schema.py
laurelin/ldap/utils.py
laurelin/ldap/validation.py
laurelin/ldap/extensible/__init__.py
laurelin/ldap/extensible/base.py
laurelin/ldap/extensible/laurelin_extensions.py
laurelin/ldap/extensible/ldap_extensions.py
laurelin/ldap/extensible/ldapobject_extensions.py
laurelin/ldap/extensible/registration.py
laurelin/ldap/extensible/user_base.py
laurelin/ldap/pyasn1/__init__.py
laurelin/ldap/pyasn1/debug.py
laurelin/ldap/pyasn1/error.py
laurelin/ldap/pyasn1/codec/__init__.py
laurelin/ldap/pyasn1/codec/ber/__init__.py
laurelin/ldap/pyasn1/codec/ber/decoder.py
laurelin/ldap/pyasn1/codec/ber/encoder.py
laurelin/ldap/pyasn1/codec/ber/eoo.py
laurelin/ldap/pyasn1/codec/cer/__init__.py
laurelin/ldap/pyasn1/codec/cer/decoder.py
laurelin/ldap/pyasn1/codec/cer/encoder.py
laurelin/ldap/pyasn1/codec/der/__init__.py
laurelin/ldap/pyasn1/codec/der/decoder.py
laurelin/ldap/pyasn1/codec/der/encoder.py
laurelin/ldap/pyasn1/codec/native/__init__.py
laurelin/ldap/pyasn1/codec/native/decoder.py
laurelin/ldap/pyasn1/codec/native/encoder.py
laurelin/ldap/pyasn1/compat/__init__.py
laurelin/ldap/pyasn1/compat/binary.py
laurelin/ldap/pyasn1/compat/calling.py
laurelin/ldap/pyasn1/compat/dateandtime.py
laurelin/ldap/pyasn1/compat/integer.py
laurelin/ldap/pyasn1/compat/octets.py
laurelin_ldap-2.0.4.dist-info/LICENSE
laurelin_ldap-2.0.4.dist-info/METADATA
laurelin_ldap-2.0.4.dist-info/WHEEL
laurelin_ldap-2.0.4.dist-info/namespace_packages.txt
laurelin_ldap-2.0.4.dist-info/top_level.txt
laurelin_ldap-2.0.4.dist-info/RECORD
